{
  "id": "Hk7InUp8mU3JRV5W9cE2",
  "title": "SEO Specialist",
  "company": "Kinetic Agency",
  "location": "Canada",
  "type": "Part-time",
  "level": "Staff",
  "salary": "$20,000-$30,000/year",
  "posted": "2025-05-19",
  "description": "<h3><strong>Kinetic Agency is Hiring – SEO Specialist (Part-time)</strong></h3><p><strong>Kinetic Agency</strong>, a digital marketing firm, boosts online visibility. We’re seeking an <strong>SEO Specialist</strong> in Vancouver to optimize client websites.</p><p><strong>About the Role:</strong> You’ll enhance search engine rankings.</p><h3><strong>Key Responsibilities</strong></h3><ul><li>Conduct <strong>SEO audits</strong>.</li><li>Optimize <strong>website content</strong>.</li><li>Analyze performance with <strong>SEMrush</strong>.</li><li>Build <strong>backlinks</strong>.</li><li>Collaborate with content teams.</li><li>Stay updated on <strong>SEO trends</strong>.</li></ul><h3><strong>Why Kinetic?</strong></h3><p>Join a <strong>dynamic team</strong>. We offer <strong>flexible hours</strong>, <strong>training</strong>, and creative projects.</p><p><strong>Benefits:</strong> Health benefits, 15 days PTO, SEO tools.</p><p>📢 <strong>#KineticCareers #SEO #DigitalMarketing #WeAreHiring</strong></p>",
  "requirements": [
    "1–3 years of experience in SEO",
    "Proficiency in SEMrush, Google Analytics",
    "Strong optimization skills",
    "Experience with content strategy",
    "Bachelor’s degree in marketing or related field"
  ],
  "verified": true
}